X53ZhangShejishiKoudaiXinlixueV1120210602/README.md
X53ZhangShejishiKoudaiXinlixueV1120210602/__init__.py
X53ZhangShejishiKoudaiXinlixueV1120210602/__main__.py
X53ZhangShejishiKoudaiXinlixueV1120210602/file.pdf
X53ZhangShejishiKoudaiXinlixueV1120210602/index.html
x53_zhang_shejishi_koudai_xinlixue_v1_1_20210602-2024.3.6.0.dist-info/METADATA
x53_zhang_shejishi_koudai_xinlixue_v1_1_20210602-2024.3.6.0.dist-info/WHEEL
x53_zhang_shejishi_koudai_xinlixue_v1_1_20210602-2024.3.6.0.dist-info/entry_points.txt
x53_zhang_shejishi_koudai_xinlixue_v1_1_20210602-2024.3.6.0.dist-info/top_level.txt
x53_zhang_shejishi_koudai_xinlixue_v1_1_20210602-2024.3.6.0.dist-info/RECORD
